sprite_util_ndthinh/__init__.py
sprite_util_ndthinh/spriteutil.py
sprite_utils-2.0.1.dist-info/LICENSE
sprite_utils-2.0.1.dist-info/METADATA
sprite_utils-2.0.1.dist-info/WHEEL
sprite_utils-2.0.1.dist-info/top_level.txt
sprite_utils-2.0.1.dist-info/RECORD
