Metadata-Version: 2.1
Name: sprite-utils
Version: 2.0.1
Summary: Spriteutil is a package contain SpriteSheet Class that can detect and create a new image contain the original image sprites
Home-page: https://github.com/intek-training-jsc/sprite-detection-ndthinh8796
Author: Thinh Nguyen
Author-email: thinh.nguyen@f4.intek.edu.vn
License: UNKNOWN
Platform: UNKNOWN
Classifier: Programming Language :: Python :: 3
Classifier: License :: OSI Approved :: MIT License
Classifier: Operating System :: OS Independent
Requires-Python: >=3.6
